ifcollector/__init__.py
ifcollector/if_functions.py
ifcollector-0.0.1.dist-info/LICENSE
ifcollector-0.0.1.dist-info/METADATA
ifcollector-0.0.1.dist-info/WHEEL
ifcollector-0.0.1.dist-info/top_level.txt
ifcollector-0.0.1.dist-info/RECORD
