Metadata-Version: 2.1
Name: ifcollector
Version: 0.0.1
Summary: A framework for creating complex if statements.
Home-page: https://github.com/jgrugru/ifcollector
Author: Jeff Gruenbaum
Author-email: jeff.gruenbaum@gmail.com
License: MIT
Keywords: if statement,if,framework,simplify,collector,ifcollector,aggregate
Platform: UNKNOWN
Classifier: License :: OSI Approved :: MIT License
Classifier: Programming Language :: Python :: 3
Classifier: Programming Language :: Python :: 3.7
